destack/__init__.py
destack-0.0.0.dist-info/METADATA
destack-0.0.0.dist-info/WHEEL
destack-0.0.0.dist-info/top_level.txt
destack-0.0.0.dist-info/RECORD
