Metadata-Version: 2.4
Name: destack
Version: 0.0.0
Summary: Destack is a personal software platform. Python SDK coming soon.
Author-email: Symbol Industries <florian@symbol.industries>
Requires-Python: >=3.12
